MANIFEST.in
README.md
setup.cfg
setup.py
versioneer.py
sanic_opentracing/__init__.py
sanic_opentracing/_version.py
sanic_opentracing/tracing.py
sanic_opentracing.egg-info/PKG-INFO
sanic_opentracing.egg-info/SOURCES.txt
sanic_opentracing.egg-info/dependency_links.txt
sanic_opentracing.egg-info/requires.txt
sanic_opentracing.egg-info/top_level.txt
tests/__init__.py
tests/sanic_app_trace_all.py
tests/sanic_app_trace_decorate.py
tests/test_sanic_api.py
tests/test_sanic_tracing_all.py
tests/test_sanic_tracing_decorate.py
tests/versioneer.py