Metadata-Version: 2.1
Name: sanic-opentracing
Version: 0.8
Summary: OpenTracing support for Sanic applications
Home-page: https://github.com/shady-robot/sanic-opentracing/
Author: Shady Robot
Author-email: darkercookies@gmail.com
License: MIT
Download-URL: https://github.com/shady-robot/sanic-opentracing/tarball/0.8
Platform: any
Classifier: Environment :: Web Environment
Classifier: Intended Audience :: Developers
Classifier: License :: OSI Approved :: MIT License
Classifier: Operating System :: OS Independent
Classifier: Programming Language :: Python
Classifier: Programming Language :: Python :: 3.6
Classifier: Programming Language :: Python :: 3.7
Classifier: Topic :: Internet :: WWW/HTTP :: Dynamic Content
Classifier: Topic :: Software Development :: Libraries :: Python Modules
Provides-Extra: tests
